{
    "Declared": {
        "Normal": [
            15,
            [
                "android.permission.INTERNET",
                "android.permission.FOREGROUND_SERVICE",
                "com.android.vending.BILLING",
                "android.permission.DOWNLOAD_WITHOUT_NOTIFICATION",
                "android.permission.ACCESS_NETWORK_STATE",
                "android.permission.ACCESS_WIFI_STATE",
                "android.permission.WAKE_LOCK",
                "android.permission.VIBRATE",
                "android.permission.USE_BIOMETRIC",
                "android.permission.USE_FINGERPRINT",
                "com.google.android.gms.permission.AD_ID",
                "android.permission.RECEIVE_BOOT_COMPLETED",
                "com.google.android.c2dm.permission.RECEIVE",
                "com.google.android.finsky.permission.BIND_GET_INSTALL_REFERRER_SERVICE",
                "android.permission.ACCESS_NOTIFICATION_POLICY"
            ]
        ],
        "Dangerous": [
            2,
            [
                "android.permission.READ_PHONE_STATE",
                "android.permission.READ_EXTERNAL_STORAGE"
            ]
        ],
        "All": [
            21,
            [
                "android.permission.INTERNET",
                "android.permission.FOREGROUND_SERVICE",
                "com.android.vending.BILLING",
                "android.permission.DOWNLOAD_WITHOUT_NOTIFICATION",
                "android.permission.POST_NOTIFICATIONS",
                "android.permission.ACCESS_NETWORK_STATE",
                "android.permission.ACCESS_WIFI_STATE",
                "android.permission.WAKE_LOCK",
                "android.permission.VIBRATE",
                "android.permission.USE_BIOMETRIC",
                "android.permission.USE_FINGERPRINT",
                "android.permission.READ_PHONE_STATE",
                "android.permission.READ_EXTERNAL_STORAGE",
                "com.google.android.gms.permission.AD_ID",
                "android.permission.RECEIVE_BOOT_COMPLETED",
                "com.google.android.c2dm.permission.RECEIVE",
                "com.google.android.finsky.permission.BIND_GET_INSTALL_REFERRER_SERVICE",
                "android.permission.USE_FULL_SCREEN_INTENT",
                "android.permission.SCHEDULE_EXACT_ALARM",
                "android.permission.BROADCAST_CLOSE_SYSTEM_DIALOGS",
                "android.permission.ACCESS_NOTIFICATION_POLICY"
            ]
        ]
    },
    "Droidbot-obtained": {
        "Normal": {
            "android.permission.WAKE_LOCK": 0,
            "android.permission.ACCESS_NETWORK_STATE": 0,
            "android.permission.GET_TASKS": 1,
            "com.google.android.providers.gsf.permission.READ_GSERVICES": 1,
            "android.permission.INTERNET": 0,
            "android.permission.USE_FINGERPRINT": 0,
            "android.permission.ACCESS_WIFI_STATE": 0,
            "android.permission.MODIFY_AUDIO_SETTINGS": 1,
            "com.google.android.finsky.permission.BIND_GET_INSTALL_REFERRER_SERVICE": 0,
            "com.google.android.gms.permission.AD_ID": 0,
            "android.permission.BLUETOOTH": 1,
            "android.permission.FOREGROUND_SERVICE": 0,
            "android.permission.DOWNLOAD_WITHOUT_NOTIFICATION": 0
        },
        "Dangerous": {
            "android.permission.GET_ACCOUNTS": 3
        },
        "filter_normal_self": {
            "android.permission.WAKE_LOCK": 0,
            "android.permission.ACCESS_NETWORK_STATE": 0,
            "android.permission.GET_TASKS": 1,
            "android.permission.INTERNET": 0,
            "android.permission.USE_FINGERPRINT": 0,
            "android.permission.ACCESS_WIFI_STATE": 0,
            "android.permission.MODIFY_AUDIO_SETTINGS": 1,
            "com.google.android.finsky.permission.BIND_GET_INSTALL_REFERRER_SERVICE": 0,
            "com.google.android.gms.permission.AD_ID": 0,
            "android.permission.FOREGROUND_SERVICE": 0,
            "android.permission.DOWNLOAD_WITHOUT_NOTIFICATION": 0
        },
        "filter_normal_self_strict": {
            "android.permission.WAKE_LOCK": 0,
            "android.permission.ACCESS_NETWORK_STATE": 0,
            "android.permission.GET_TASKS": 1,
            "android.permission.USE_FINGERPRINT": 0,
            "android.permission.ACCESS_WIFI_STATE": 0,
            "android.permission.MODIFY_AUDIO_SETTINGS": 1,
            "android.permission.FOREGROUND_SERVICE": 0,
            "android.permission.INTERNET": 0,
            "android.permission.DOWNLOAD_WITHOUT_NOTIFICATION": 0
        },
        "add_dangerous_request": {
            "android.permission.GET_ACCOUNTS": 3
        }
    }
}